Iverilog/Iverilog_basic/1_4demux.v
module nand3(input wire a,b,c,output wire d);
assign d=(a&b&c);
endmodule

module decoder24(input wire a,b,c,output wire d,e,f,g);
wire t1,t2,t3;
assign t1=~a;
assign t2=~b;
assign t3=c;

nand3 n0(t1,t2,t3,d);
nand3 n1(t1,b,t3,e);
nand3 n2(a,t2,t3,f);
nand3 n3(a,b,t3,g);

endmodule

Iverilog/Iverilog_basic/tb_24decoder.v
module tb;
reg t_a,t_b,t_c;
wire a,b,c,d;

decoder24 x(.a(t_a),.b(t_b),.c(t_c),.d(a),.e(b),.f(c),.g(d));
initial begin
$dumpfile("dump_decoder24.vcd");
$dumpvars(0,tb);
end
initial begin
$monitor(t_c,"  ",t_a," ",t_b,"   ",a," ",b," ",c," ",d);

t_c=1'b1;
t_a=1'b0;
t_b=1'b0;
#10
t_c=1'b1;
t_a=1'b0;
t_b=1'b1;
#10
t_c=1'b1;
t_a=1'b1;
t_b=1'b0;
#10
t_c=1'b1;
t_a=1'b1;
t_b=1'b1;
#10
t_c=1'b0;
t_a=1'b0;
t_b=1'b0;
#10
t_c=1'b0;
t_a=1'b0;
t_b=1'b1;
#10
t_c=1'b0;
t_a=1'b1;
t_b=1'b0;
#10
t_c=1'b0;
t_a=1'b1;
t_b=1'b1;

end
endmodule

Iverilog/Iverilog_basic/dump_decoder24.vcd
$date
	Fri Aug 26 17:05:27 2022
$end
$version
	Icarus Verilog
$end
$timescale
	1s
$end
$scope module tb $end
$var wire 1 ! d $end
$var wire 1 " c $end
$var wire 1 # b $end
$var wire 1 $ a $end
$var reg 1 % t_a $end
$var reg 1 & t_b $end
$var reg 1 ' t_c $end
$scope module x $end
$var wire 1 % a $end
$var wire 1 & b $end
$var wire 1 ' c $end
$var wire 1 ( t1 $end
$var wire 1 ) t2 $end
$var wire 1 * t3 $end
$var wire 1 ! g $end
$var wire 1 " f $end
$var wire 1 # e $end
$var wire 1 $ d $end
$scope module n0 $end
$var wire 1 ( a $end
$var wire 1 ) b $end
$var wire 1 * c $end
$var wire 1 $ d $end
$upscope $end
$scope module n1 $end
$var wire 1 ( a $end
$var wire 1 & b $end
$var wire 1 * c $end
$var wire 1 # d $end
$upscope $end
$scope module n2 $end
$var wire 1 % a $end
$var wire 1 ) b $end
$var wire 1 * c $end
$var wire 1 " d $end
$upscope $end
$scope module n3 $end
$var wire 1 % a $end
$var wire 1 & b $end
$var wire 1 * c $end
$var wire 1 ! d $end
$upscope $end
$upscope $end
$upscope $end
$enddefinitions $end
#0
$dumpvars
0*
1)
1(
1'
0&
0%
1$
1#
1"
1!
$end
#10
0)
1&
#20
1)
0(
0&
1%
#30
0)
1&
#40
0$
1)
1(
1*
0&
0%
0'
#50
1$
0#
0)
1&
#60
0"
1#
1)
0(
0&
1%
#70
1"
0!
0)
1&
